{"name":"Codechef","tagline":"Submissions for CodeChef","body":"CodeChef\r\n===============\r\nSubmissions for codechef\r\n\r\n\r\nAuthor\r\n------\r\nRishi Dua <http://github.com/rishirdua>\r\n\r\n\r\nContribute\r\n----------\r\nFeel free to fork and use my code. Feedback and suggestions are always welcome\r\n\r\n\r\nLicense\r\n-------\r\nThis project is licensed under the terms of the WTFPL license. See LICENCE.txt for details\r\n","google":"","note":"Don't delete this file! It's used internally to help with page regeneration."}